{
  "_fv": 10,
  "_type": "gun",
  "definition": {
    "renderType": 0,
    "texture": "wookiegreande",
    "customModelName": "Normal",
    "name": "Wookiee power charge",
    "specialInfo": [],
    "creativeTab": {
      "value": "COMBAT"
    },
    "stackSize": 1,
    "ammoItem": {
      "value": ""
    },
    "shootConstantly": false,
    "usageCount": 1,
    "actionSound": {
      "value": "entity.arrow.shoot"
    },
    "hasGlow": false,
    "enableMeleeDamage": false,
    "damageVsEntity": 0.0,
    "bulletPower": 1.0,
    "bulletDamage": 5.0,
    "bulletKnockback": 5,
    "bulletParticles": false,
    "bulletIgnitesFire": false,
    "bulletItemTexture": {
      "value": "CUSTOM:Plastoidalloy"
    },
    "bulletModel": "Default",
    "customBulletModelTexture": ""
  }
}